peleffy/__init__.py
peleffy/_version.py
peleffy/main.py
peleffy/data/complexes/5XXD_SAM.pdb
peleffy/data/complexes/LIG1_LIG2.pdb
peleffy/data/complexes/LYS_BNZ.pdb
peleffy/data/complexes/complex_test.pdb
peleffy/data/forcefields/GBSA_OBC1-1.0.offxml
peleffy/data/forcefields/GBSA_OBC2-1.0.offxml
peleffy/data/ligands/BHP.mae
peleffy/data/ligands/BHP.pdb
peleffy/data/ligands/BNZ.pdb
peleffy/data/ligands/LIG1.pdb
peleffy/data/ligands/LIG2.pdb
peleffy/data/ligands/SAM.pdb
peleffy/data/ligands/acetylene.pdb
peleffy/data/ligands/ammonium.pdb
peleffy/data/ligands/benzamidine.pdb
peleffy/data/ligands/benzene.mae
peleffy/data/ligands/benzene.pdb
peleffy/data/ligands/benzene_without_connectivity.pdb
peleffy/data/ligands/ethylene.mae
peleffy/data/ligands/ethylene.pdb
peleffy/data/ligands/ligand.pdb
peleffy/data/ligands/malonate.mae
peleffy/data/ligands/malonate.pdb
peleffy/data/ligands/methane.pdb
peleffy/data/ligands/modified_sidechain.pdb
peleffy/data/ligands/octafluorocyclobutane.pdb
peleffy/data/ligands/oleic_acid.pdb
peleffy/data/ligands/propionic_acid.pdb
peleffy/data/ligands/toluene.mae
peleffy/data/ligands/toluene.pdb
peleffy/data/ligands/trimethylglycine.pdb
peleffy/data/ligands/trimethylglycine_moved.pdb
peleffy/data/parameters/ETH.conformation
peleffy/data/parameters/ETH.dihedral
peleffy/data/parameters/OBCparam.json
peleffy/data/parameters/f14_sgbnp.param
peleffy/data/parameters/similarity.param
peleffy/data/parameters/solventParamsHCTOBC.txt
peleffy/data/tests/CO1_ffld_output.txt
peleffy/data/tests/ETL_ffld_output.txt
peleffy/data/tests/ETL_openff-1.2.1_opls2005_parameters1.json
peleffy/data/tests/ETL_openff-1.2.1_opls2005_parameters2.json
peleffy/data/tests/ETL_openff-1.2.1_parameters.json
peleffy/data/tests/ETL_opls2005_parameters.json
peleffy/data/tests/ETL_solventParamsHCTOBC.txt
peleffy/data/tests/MAL_ffld_output.txt
peleffy/data/tests/MAL_solventParamsHCTOBC.txt
peleffy/data/tests/MAT.mae
peleffy/data/tests/MAT.pdb
peleffy/data/tests/MET_ffld_output.txt
peleffy-1.4.4.dist-info/LICENSE
peleffy-1.4.4.dist-info/METADATA
peleffy-1.4.4.dist-info/WHEEL
peleffy-1.4.4.dist-info/top_level.txt
peleffy-1.4.4.dist-info/RECORD
