Metadata-Version: 2.1
Name: peleffy
Version: 1.4.4
Summary: PELE Force Field Yielder
Home-page: http://github.com/martimunicoy/peleffy
Author: Martí Municoy
Author-email: martimunicoy@gmail.com
License: MIT
Keywords: molecular mechanics,forcefield,potential energy
Classifier: Development Status :: 5 - Production/Stable
Classifier: Natural Language :: English
Classifier: Environment :: Console
Classifier: Intended Audience :: Science/Research
Classifier: Topic :: Utilities
Classifier: License :: OSI Approved :: MIT License
Classifier: Programming Language :: Python :: 3
Classifier: Operating System :: Unix
Classifier: Operating System :: MacOS
License-File: LICENSE
